strotools/ballboi/__init__.py
strotools/ballboi/cli.py
strotools/ballboi/nfl_retriever.py
strotools/ballboi/retriever.py
strotools.ballboi-0.0.41.data/scripts/ballboi
strotools.ballboi-0.0.41.dist-info/LICENSE
strotools.ballboi-0.0.41.dist-info/METADATA
strotools.ballboi-0.0.41.dist-info/WHEEL
strotools.ballboi-0.0.41.dist-info/top_level.txt
strotools.ballboi-0.0.41.dist-info/RECORD
